loggerXio/__init__.py
loggerXio/core.py
loggerxio-1.0.8.dist-info/licenses/LICENSE
loggerxio-1.0.8.dist-info/METADATA
loggerxio-1.0.8.dist-info/WHEEL
loggerxio-1.0.8.dist-info/top_level.txt
loggerxio-1.0.8.dist-info/RECORD
