Metadata-Version: 2.4
Name: loggerXio
Version: 1.0.8
Summary: Telegram-Powered Python Logger - Send Logs & print() Output Straight to Your Chat in Real Time!
Home-page: https://github.com/wxxoxo/loggerXio
Author: Arise
Author-email: arise.wxxoxo@gmail.com
License: MIT
Project-URL: Documentation, https://github.com/wxxoxo/loggerXio#readme
Project-URL: Source, https://github.com/wxxoxo/loggerXio
Project-URL: Support, https://t.me/wxxoxo
Keywords: telegram, telebot, pytelegrambotapi, logger, logging, log, logs,,python-logger, python-logging, python-log, real-time, realtime,,live-logging, live-logger, telegram-logger, telegram-logging,,chat-logger, chat-logging, bot-logger, bot-logging,,monitoring, monitor, remote-logging, remote-logger,,print-capture, capture-print, capture-output,,sysout, stderr, stdout,,debugging, debug, debug-tool, debug-logger,,system-logger, application-logger,,python-bot, telegram-bot,,automation, automati
Requires-Python: >=3.7
License-File: LICENSE
Requires-Dist: pyTelegramBotAPI>=4.0.0
Dynamic: license-file
